{
  "volto-slate": {
    "url": "https://github.com/eea/volto-slate.git",
    "branch": "master",
    "path": "src"
  },
  "volto-tabsblock": {
    "url": "https://github.com/eea/volto-tabsblock.git",
    "branch": "master",
    "path": "src",
    "package": "@eeacms/volto-tabs-block"
  },
  "volto-slate-metadata-mentions": {
    "url": "https://github.com/eea/volto-slate-metadata-mentions.git",
    "branch": "develop",
    "path": "src"
  },
  "volto-widgets-view": {
    "url": "https://github.com/eea/volto-widgets-view.git",
    "package": "@eeacms/volto-widgets-view",
    "branch": "develop",
    "path": "src"
  },
  "volto-object-widget": {
    "url": "https://github.com/eea/volto-object-widget.git",
    "package": "@eeacms/volto-object-widget",
    "branch": "master",
    "path": "src"
  },
  "volto-slate-footnote": {
    "url": "https://github.com/eea/volto-slate-footnote.git",
    "package": "@eeacms/volto-slate-footnote",
    "branch": "master",
    "path": "src"
  },
  "volto-blocks-form": {
    "url": "https://github.com/tiberiuichim/volto-blocks-form.git",
    "package": "@eeacms/volto-blocks-form",
    "branch": "master",
    "path": "src"
  }
}
